kwikapi/__init__.py
kwikapi/api.py
kwikapi/apidoc.py
kwikapi/auth.py
kwikapi/client.py
kwikapi/exception.py
kwikapi/protocols.py
kwikapi/utils.py
kwikapi-0.5.15.dist-info/LICENSE
kwikapi-0.5.15.dist-info/METADATA
kwikapi-0.5.15.dist-info/WHEEL
kwikapi-0.5.15.dist-info/top_level.txt
kwikapi-0.5.15.dist-info/RECORD
