Metadata-Version: 2.1
Name: kwikapi
Version: 0.5.15
Summary: Quickly build API services to expose functionality in Python.
Home-page: https://github.com/deep-compute/kwikapi
Author: Deep Compute, LLC
Author-email: contact@deepcompute.com
License: MIT License
Download-URL: https://github.com/deep-compute/kwikapi/tarball/0.5.15
Platform: UNKNOWN
Classifier: Environment :: Web Environment
Classifier: Intended Audience :: Developers
Classifier: License :: OSI Approved :: MIT License
Classifier: Operating System :: OS Independent
Classifier: Programming Language :: Python
Classifier: Programming Language :: Python :: 3
Classifier: Programming Language :: Python :: 3.5
Classifier: Topic :: Internet :: WWW/HTTP
Classifier: Topic :: Internet :: WWW/HTTP :: Dynamic Content
Requires-Dist: msgpack-python (==0.5.1)
Requires-Dist: deeputil (==0.2.9)
Requires-Dist: numpy (==1.15.1)
Requires-Dist: future (==0.16.0)
Requires-Dist: requests (>=2.18.4)
Provides-Extra: all
Requires-Dist: kwikapi-django (==0.2.6) ; extra == 'all'
Requires-Dist: kwikapi-tornado (==0.3.7) ; extra == 'all'
Provides-Extra: django
Requires-Dist: kwikapi-django (==0.2.6) ; extra == 'django'
Provides-Extra: tornado
Requires-Dist: kwikapi-tornado (==0.3.8) ; extra == 'tornado'
